whisperingscript/__init__.py
whisperingscript/automation.py
whisperingscript/main.py
whisperingscript-0.1.0.dist-info/licenses/LICENSE
whisperingscript-0.1.0.dist-info/METADATA
whisperingscript-0.1.0.dist-info/WHEEL
whisperingscript-0.1.0.dist-info/entry_points.txt
whisperingscript-0.1.0.dist-info/top_level.txt
whisperingscript-0.1.0.dist-info/RECORD
