Metadata-Version: 2.4
Name: whisperingscript
Version: 0.1.0
Summary: Browser automation script for whispering.bradenwong.com transcription service
Author-email: Martin Paul Eve <martin@example.com>
Maintainer-email: Martin Paul Eve <martin@example.com>
License: MIT
Project-URL: Homepage, https://github.com/martin/whisperingscript
Project-URL: Repository, https://github.com/martin/whisperingscript
Project-URL: Issues, https://github.com/martin/whisperingscript/issues
Project-URL: Documentation, https://github.com/martin/whisperingscript#readme
Keywords: automation,transcription,selenium,browser,whisper
Classifier: Development Status :: 4 - Beta
Classifier: Intended Audience :: Developers
Classifier: Intended Audience :: End Users/Desktop
Classifier: License :: OSI Approved :: MIT License
Classifier: Operating System :: OS Independent
Classifier: Programming Language :: Python :: 3
Classifier: Programming Language :: Python :: 3.8
Classifier: Programming Language :: Python :: 3.9
Classifier: Programming Language :: Python :: 3.10
Classifier: Programming Language :: Python :: 3.11
Classifier: Programming Language :: Python :: 3.12
Classifier: Topic :: Internet :: WWW/HTTP :: Browsers
Classifier: Topic :: Multimedia :: Sound/Audio :: Speech
Classifier: Topic :: Office/Business
Classifier: Topic :: Software Development :: Libraries :: Python Modules
Requires-Python: >=3.8
License-File: LICENSE
Requires-Dist: selenium>=4.0.0
Requires-Dist: pyperclip>=1.8.0
Requires-Dist: plyer>=2.0.0
Provides-Extra: dev
Requires-Dist: pytest>=7.0.0; extra == "dev"
Requires-Dist: pytest-cov>=4.0.0; extra == "dev"
Requires-Dist: black>=22.0.0; extra == "dev"
Requires-Dist: flake8>=5.0.0; extra == "dev"
Requires-Dist: mypy>=1.0.0; extra == "dev"
Dynamic: license-file
